vector_tompy/__init__.py
vector_tompy/area2.py
vector_tompy/exceptions.py
vector_tompy/line2.py
vector_tompy/vector2.py
vector_tompy-2025.10.10.18.43.dist-info/METADATA
vector_tompy-2025.10.10.18.43.dist-info/WHEEL
vector_tompy-2025.10.10.18.43.dist-info/RECORD
