Metadata-Version: 2.4
Name: vector-tompy
Version: 2025.10.10.18.43
Summary: Vectors for tompy projects
Author: tompy
Classifier: Development Status :: 3 - Alpha
Classifier: Intended Audience :: Developers
Classifier: License :: OSI Approved :: GNU General Public License v3 (GPLv3)
Classifier: Operating System :: OS Independent
Classifier: Programming Language :: Python :: 3.9
Requires-Python: >=3.9
Requires-Dist: angle-tompy>=2025.10.8.23.47
Requires-Dist: iterable-tompy>=2025.9.16.21.41
Requires-Dist: math-tompy>=2025.9.25.18.9
Requires-Dist: sympy>=1.14.0
